{"is_source_file": true, "format": "Python", "description": "This file implements an interactive SQLite database shell for managing and inspecting the 'social_dashboard_database'. It provides functions for listing tables, showing schemas, describing table structures, and executing SQL commands interactively.", "external_files": ["sqlite3"], "external_methods": ["sqlite3.connect", "cursor.execute", "cursor.fetchall", "sys.exit", "print"], "published": [], "classes": [], "methods": [{"name": "print_help()", "description": "Displays help information about available commands in the interactive shell.", "scope": "", "scopeKind": ""}, {"name": "list_tables(cursor)", "description": "Lists all user-defined tables in the database.", "scope": "", "scopeKind": ""}, {"name": "show_schema(cursor, table_name=None)", "description": "Shows the CREATE SQL statements for tables; can show all or specific table.", "scope": "", "scopeKind": ""}, {"name": "describe_table(cursor, table_name)", "description": "Displays the structure of a specified table, including column info.", "scope": "", "scopeKind": ""}, {"name": "execute_query(cursor, query)", "description": "Executes a provided SQL query and displays results or affected row count.", "scope": "", "scopeKind": ""}, {"name": "main()", "description": "Main function establishing the interactive loop for user input and command execution.", "scope": "", "scopeKind": ""}], "calls": ["sqlite3.connect", "cursor.execute", "cursor.fetchall", "sys.exit", "print", "input"], "search-terms": ["sqlite shell", "interactive database", "social_dashboard_database", "db_shell.py", "SQL commands", "database inspection"], "state": 2, "file_id": 4, "knowledge_revision": 14, "git_revision": "5c6d39516b9cc7632c850698fd07eb0b64546825", "ctags": [{"_type": "tag", "name": "DB_NAME", "path": "/tmp/kavia/workspace/code-generation/user-approval-system-711-720/social_dashboard_database/db_shell.py", "pattern": "/^DB_NAME = \"myapp.db\"$/", "language": "Python", "kind": "variable"}, {"_type": "tag", "name": "describe_table", "path": "/tmp/kavia/workspace/code-generation/user-approval-system-711-720/social_dashboard_database/db_shell.py", "pattern": "/^def describe_table(cursor, table_name):$/", "language": "Python", "kind": "function", "signature": "(cursor, table_name)"}, {"_type": "tag", "name": "execute_query", "path": "/tmp/kavia/workspace/code-generation/user-approval-system-711-720/social_dashboard_database/db_shell.py", "pattern": "/^def execute_query(cursor, query):$/", "language": "Python", "kind": "function", "signature": "(cursor, query)"}, {"_type": "tag", "name": "list_tables", "path": "/tmp/kavia/workspace/code-generation/user-approval-system-711-720/social_dashboard_database/db_shell.py", "pattern": "/^def list_tables(cursor):$/", "language": "Python", "kind": "function", "signature": "(cursor)"}, {"_type": "tag", "name": "main", "path": "/tmp/kavia/workspace/code-generation/user-approval-system-711-720/social_dashboard_database/db_shell.py", "pattern": "/^def main():$/", "language": "Python", "kind": "function", "signature": "()"}, {"_type": "tag", "name": "print_help", "path": "/tmp/kavia/workspace/code-generation/user-approval-system-711-720/social_dashboard_database/db_shell.py", "pattern": "/^def print_help():$/", "language": "Python", "kind": "function", "signature": "()"}, {"_type": "tag", "name": "show_schema", "path": "/tmp/kavia/workspace/code-generation/user-approval-system-711-720/social_dashboard_database/db_shell.py", "pattern": "/^def show_schema(cursor, table_name=None):$/", "language": "Python", "kind": "function", "signature": "(cursor, table_name=None)"}], "hash": "e8f65bc957bb79d7b7c92f8ac72aaf30", "format-version": 4, "code-base-name": "social_dashboard_database", "filename": "social_dashboard_database/db_shell.py", "fields": [{"name": "DB_NAME = \"myapp.db\"", "scope": "", "scopeKind": "", "description": "unavailable"}], "revision_history": [{"14": "5c6d39516b9cc7632c850698fd07eb0b64546825"}]}